{"US Dollar":{"sell":"44570","buy":"44470"},"Euro":{"sell":"48555","buy":"48405"},"British Pound":{"sell":"55200","buy":"55000"},"Swiss Franc":{"sell":"48460","buy":"48310"},"Canadian Dollar":{"sell":"33255","buy":"33155"},"Australian Dollar":{"sell":"31660","buy":"31560"},"Swedish Krona":{"sell":"4350","buy":"4335"},"Norwegian Krone":{"sell":"4510","buy":"4495"},"Russian Ruble":{"sell":"645","buy":"640"},"Thai Baht":{"sell":"1360","buy":"1355"},"Singapore Dollar":{"sell":"33960","buy":"33860"},"Hong Kong Dollar":{"sell":"5690","buy":"5660"},"Azerbaijani Manat":{"sell":"26180","buy":"26080"},"Armenian Dram":{"sell":"1130","buy":"1125"},"Danish Krone":{"sell":"6525","buy":"6505"},"UAE Dirham":{"sell":"12135","buy":"12115"},"Japanese Yen":{"sell":"3430","buy":"3420"},"Turkish Lira":{"sell":"2370","buy":"2350"},"Chinese Yuan":{"sell":"6570","buy":"6550"},"KSA Riyal":{"sell":"11875","buy":"11845"},"Indian Rupee":{"sell":"545","buy":"545"},"Ringgit":{"sell":"10500","buy":"10470"},"Afghan Afghani":{"sell":"505","buy":"500"},"Kuwaiti Dinar":{"sell":"146055","buy":"145655"},"Iraqi Dinar":{"sell":"3070","buy":"3060"},"Bahraini Dinar":{"sell":"118235","buy":"117735"},"Omani Rial":{"sell":"115935","buy":"115635"},"Qatari Riyal":{"sell":"12240","buy":"12210"},"Azadi":{"sell":"23000000","buy":"22500000"},"Emami":{"sell":"24700000","buy":"24000000"},"\u00bd Azadi":{"sell":"14400000","buy":"13900000"},"\u00bc Azadi":{"sell":"9150000","buy":"8750000"},"Gerami":{"sell":"4800000","buy":"4500000"},"Gold Gram":{"sell":"2119210"},"Gold Mithqal":{"sell":"9180000"},"Gold Ounce":{"sell":"1937.09"},"Bitcoin":{"sell":"22941.04"}}
