{"US Dollar":{"sell":"42400","buy":"42300"},"Euro":{"sell":"45275","buy":"45125"},"British Pound":{"sell":"51045","buy":"50845"},"Swiss Franc":{"sell":"45960","buy":"45810"},"Canadian Dollar":{"sell":"31350","buy":"31250"},"Australian Dollar":{"sell":"28830","buy":"28730"},"Swedish Krona":{"sell":"4085","buy":"4070"},"Norwegian Krone":{"sell":"4310","buy":"4295"},"Russian Ruble":{"sell":"595","buy":"590"},"Thai Baht":{"sell":"1225","buy":"1220"},"Singapore Dollar":{"sell":"31635","buy":"31535"},"Hong Kong Dollar":{"sell":"5440","buy":"5410"},"Azerbaijani Manat":{"sell":"24935","buy":"24835"},"Armenian Dram":{"sell":"1075","buy":"1070"},"Danish Krone":{"sell":"6090","buy":"6070"},"UAE Dirham":{"sell":"11545","buy":"11525"},"Japanese Yen":{"sell":"3215","buy":"3205"},"Turkish Lira":{"sell":"2265","buy":"2245"},"Chinese Yuan":{"sell":"6145","buy":"6125"},"KSA Riyal":{"sell":"11270","buy":"11240"},"Indian Rupee":{"sell":"515","buy":"515"},"Ringgit":{"sell":"9625","buy":"9595"},"Afghan Afghani":{"sell":"477","buy":"472"},"Kuwaiti Dinar":{"sell":"138540","buy":"138140"},"Iraqi Dinar":{"sell":"2910","buy":"2900"},"Bahraini Dinar":{"sell":"112455","buy":"111955"},"Omani Rial":{"sell":"110125","buy":"109825"},"Qatari Riyal":{"sell":"11645","buy":"11615"},"Azadi":{"sell":"21000000","buy":"20000000"},"Emami":{"sell":"23000000","buy":"22500000"},"\u00bd Azadi":{"sell":"13000000","buy":"12700000"},"\u00bc Azadi":{"sell":"10000000","buy":"9600000"},"Gerami":{"sell":"4700000","buy":"4300000"},"Gold Gram":{"sell":"1920679"},"Gold Mithqal":{"sell":"8320000"},"Gold Ounce":{"sell":"1818.6"},"Bitcoin":{"sell":"16491.68"}}
