{"US Dollar":{"sell":"43020","buy":"42920"},"Euro":{"sell":"46780","buy":"46630"},"British Pound":{"sell":"52975","buy":"52775"},"Swiss Franc":{"sell":"46590","buy":"46440"},"Canadian Dollar":{"sell":"32195","buy":"32095"},"Australian Dollar":{"sell":"30330","buy":"30230"},"Swedish Krona":{"sell":"4210","buy":"4195"},"Norwegian Krone":{"sell":"4360","buy":"4345"},"Russian Ruble":{"sell":"625","buy":"620"},"Thai Baht":{"sell":"1310","buy":"1305"},"Singapore Dollar":{"sell":"32590","buy":"32490"},"Hong Kong Dollar":{"sell":"5495","buy":"5465"},"Azerbaijani Manat":{"sell":"25315","buy":"25215"},"Armenian Dram":{"sell":"1085","buy":"1080"},"Danish Krone":{"sell":"6290","buy":"6270"},"UAE Dirham":{"sell":"11710","buy":"11690"},"Japanese Yen":{"sell":"3305","buy":"3295"},"Turkish Lira":{"sell":"2285","buy":"2265"},"Chinese Yuan":{"sell":"6340","buy":"6320"},"KSA Riyal":{"sell":"11455","buy":"11425"},"Indian Rupee":{"sell":"525","buy":"525"},"Ringgit":{"sell":"10040","buy":"10010"},"Afghan Afghani":{"sell":"480","buy":"475"},"Kuwaiti Dinar":{"sell":"140870","buy":"140470"},"Iraqi Dinar":{"sell":"2945","buy":"2935"},"Bahraini Dinar":{"sell":"114110","buy":"113610"},"Omani Rial":{"sell":"111735","buy":"111435"},"Qatari Riyal":{"sell":"11815","buy":"11785"},"Azadi":{"sell":"22300000","buy":"21700000"},"Emami":{"sell":"23400000","buy":"22700000"},"\u00bd Azadi":{"sell":"14000000","buy":"13400000"},"\u00bc Azadi":{"sell":"9000000","buy":"8000000"},"Gerami":{"sell":"4400000","buy":"4000000"},"Gold Gram":{"sell":"2037258"},"Gold Mithqal":{"sell":"8825000"},"Gold Ounce":{"sell":"1931.03"},"Bitcoin":{"sell":"22636.44"}}
